dltctl/__init__.py
dltctl/cli.py
dltctl/version.py
dltctl/api/__init__.py
dltctl/api/jobs.py
dltctl/api/permissions.py
dltctl/api/pipelines.py
dltctl/api/workspace.py
dltctl/core/__init__.py
dltctl/core/commands.py
dltctl/core/constants.py
dltctl/core/helpers.py
dltctl/types/__init__.py
dltctl/types/events.py
dltctl/types/permissions.py
dltctl/types/pipelines.py
dltctl/types/project.py
dltctl/utils/__init__.py
dltctl/utils/print_utils.py
dltctl-0.2.dist-info/LICENSE
dltctl-0.2.dist-info/METADATA
dltctl-0.2.dist-info/WHEEL
dltctl-0.2.dist-info/entry_points.txt
dltctl-0.2.dist-info/top_level.txt
dltctl-0.2.dist-info/RECORD
