Metadata-Version: 2.1
Name: dltctl
Version: 0.2
Summary: A command line interface for Databricks Delta Live Tables
Home-page: https://github.com/bkvarda/dltctl
Author: Brandon Kvarda
Author-email: brandon@databricks.com
License: Apache License 2.0
Keywords: databricks dlt delta live tables
Platform: UNKNOWN
Classifier: Intended Audience :: Developers
Classifier: Intended Audience :: System Administrators
Classifier: Programming Language :: Python :: 3.6
Classifier: Programming Language :: Python :: 3.7
Classifier: Programming Language :: Python :: 3.8
Classifier: Programming Language :: Python :: 3.9
Classifier: Programming Language :: Python :: 3.10
Classifier: License :: OSI Approved :: Apache Software License
Requires-Dist: databricks-cli (>=0.17.3)
Requires-Dist: colorama (>=0.4.5)
Requires-Dist: PyYAML (==6.0)
